awakatime/__init__.py
awakatime/awakatime.py
awakatime/utils.py
awakatime-1.1.10.dist-info/LICENSE
awakatime-1.1.10.dist-info/METADATA
awakatime-1.1.10.dist-info/WHEEL
awakatime-1.1.10.dist-info/RECORD
