Metadata-Version: 2.1
Name: awakatime
Version: 1.1.10
Summary: A simple async wrapper for the Wakatime API
Home-page: https://github.com/controlado/awakatime
License: MIT
Keywords: wakatime,api-wrapper,async
Author: Yan Gabriel
Author-email: yangabrielogy@gmail.com
Requires-Python: >=3.11,<4.0
Classifier: Development Status :: 5 - Production/Stable
Classifier: Framework :: AsyncIO
Classifier: License :: OSI Approved :: MIT License
Classifier: Natural Language :: English
Classifier: Natural Language :: Portuguese (Brazilian)
Classifier: Operating System :: OS Independent
Classifier: Programming Language :: Python :: 3
Classifier: Programming Language :: Python :: 3.11
Requires-Dist: aiohttp[speedups] (>=3.8.5,<4.0.0)
Project-URL: Documentation, https://awakatime.readthedocs.io/en/latest/
Project-URL: Repository, https://github.com/controlado/awakatime
